[
  {
    "money": 110,
    "prob": 0.65
  },
  {
    "item": 4000047,
    "prob": 0.01
  },
  {
    "item": 2000003,
    "prob": 0.02
  },
  {
    "item": 2041017,
    "prob": 2E-05
  },
  {
    "item": 1432003,
    "prob": 8E-05
  },
  {
    "item": 1002048,
    "prob": 0.0002
  },
  {
    "item": 1032002,
    "prob": 0.0001
  },
  {
    "item": 1082008,
    "prob": 0.0001
  },
  {
    "item": 1092007,
    "prob": 8E-05
  },
  {
    "item": 4000107,
    "prob": 0.4
  },
  {
    "item": 4131001,
    "prob": 8E-05
  },
  {
    "item": 2002009,
    "prob": 0.003
  },
  {
    "item": 2060000,
    "max": 30,
    "min": 20,
    "prob": 0.008
  },
  {
    "item": 2061000,
    "max": 30,
    "min": 20,
    "prob": 0.008
  },
  {
    "item": 4020001,
    "prob": 0.003
  },
  {
    "item": 4004001,
    "prob": 0.0008
  },
  {
    "item": 2000002,
    "prob": 0.02
  }
]